odoo/addons/edi_sale_oca/README.rst
odoo/addons/edi_sale_oca/__init__.py
odoo/addons/edi_sale_oca/__manifest__.py
odoo/addons/edi_sale_oca/data/edi_configuration.xml
odoo/addons/edi_sale_oca/demo/edi_backend.xml
odoo/addons/edi_sale_oca/demo/edi_configuration.xml
odoo/addons/edi_sale_oca/demo/edi_exchange_type.xml
odoo/addons/edi_sale_oca/i18n/edi_sale_oca.pot
odoo/addons/edi_sale_oca/i18n/it.po
odoo/addons/edi_sale_oca/models/__init__.py
odoo/addons/edi_sale_oca/models/res_partner.py
odoo/addons/edi_sale_oca/models/sale_order.py
odoo/addons/edi_sale_oca/readme/CONTRIBUTORS.md
odoo/addons/edi_sale_oca/readme/CREDITS.md
odoo/addons/edi_sale_oca/readme/DESCRIPTION.md
odoo/addons/edi_sale_oca/static/description/icon.png
odoo/addons/edi_sale_oca/static/description/index.html
odoo/addons/edi_sale_oca/tests/__init__.py
odoo/addons/edi_sale_oca/tests/common.py
odoo/addons/edi_sale_oca/tests/test_generate.py
odoo/addons/edi_sale_oca/tests/test_order.py
odoo/addons/edi_sale_oca/views/edi_exchange_record.xml
odoo/addons/edi_sale_oca/views/res_partner.xml
odoo/addons/edi_sale_oca/views/sale_order.xml
odoo_addon_edi_sale_oca-18.0.1.0.1.dist-info/METADATA
odoo_addon_edi_sale_oca-18.0.1.0.1.dist-info/WHEEL
odoo_addon_edi_sale_oca-18.0.1.0.1.dist-info/top_level.txt
odoo_addon_edi_sale_oca-18.0.1.0.1.dist-info/RECORD
